pandaxt/__init__.py
pandaxt/core.py
pandaxt/decorators.py
pandaxt/utils.py
pandaxt-0.1.6.dist-info/LICENSE
pandaxt-0.1.6.dist-info/METADATA
pandaxt-0.1.6.dist-info/WHEEL
pandaxt-0.1.6.dist-info/dependency_links.txt
pandaxt-0.1.6.dist-info/top_level.txt
pandaxt-0.1.6.dist-info/RECORD
