Metadata-Version: 2.1
Name: pandaxt
Version: 0.1.6
Summary: 
Requires-Dist: requests
Requires-Dist: pandas
Requires-Dist: ccxt
Requires-Dist: tulipy
Requires-Dist: begins
Requires-Dist: py-term
